helpjuice/__init__.py
helpjuice/api/__init__.py
helpjuice/api/activity.py
helpjuice/api/article.py
helpjuice/api/category.py
helpjuice/api/group.py
helpjuice/api/schema.py
helpjuice/api/search.py
helpjuice/api/settings.py
helpjuice/api/user.py
helpjuice/client.py
helpjuice/errors.py
helpjuice-3.0.5.dist-info/LICENSE
helpjuice-3.0.5.dist-info/METADATA
helpjuice-3.0.5.dist-info/WHEEL
helpjuice-3.0.5.dist-info/RECORD
