Metadata-Version: 2.1
Name: helpjuice
Version: 3.0.5
Summary: Python Helpjuice API Wrapper.
Home-page: https://github.com/samamorgan/helpjuice
License: GPL-3.0-or-later
Author: Sam Morgan
Author-email: sam@samamorgan.com
Requires-Python: >=3.8,<4.0
Classifier: Development Status :: 5 - Production/Stable
Classifier: Intended Audience :: Developers
Classifier: License :: OSI Approved :: GNU General Public License v3 (GPLv3)
Classifier: License :: OSI Approved :: GNU General Public License v3 or later (GPLv3+)
Classifier: Operating System :: OS Independent
Classifier: Programming Language :: Python :: 3
Classifier: Programming Language :: Python :: 3.8
Classifier: Programming Language :: Python :: 3.9
Classifier: Programming Language :: Python :: 3.10
Classifier: Programming Language :: Python :: 3.11
Classifier: Programming Language :: Python :: 3.12
Requires-Dist: importlib-metadata (>=5.0.0,<6.0.0)
Requires-Dist: requests (>=2.28.1,<3.0.0)
Project-URL: Bug Tracker, https://github.com/samamorgan/helpjuice/issues
Project-URL: Documentation, https://helpjuice.readthedocs.io
Project-URL: Funding, https://github.com/sponsors/samamorgan
Project-URL: Repository, https://github.com/samamorgan/helpjuice
